Workbook

Sheet Assumptions
A1: Hiero — 5-Year Model Assumptions
A2: Blue = input you can change · Yellow = key assumption to defend on stage · All other sheets recalculate from here
A4: Driver | B4: Unit | C4: Y1 (2027) | D4: Y2 (2028) | E4: Y3 (2029) | F4: Y4 (2030) | G4: Y5 (2031) | H4: Basis / note
A5: Users (B2C)
A6: Registered users (cumulative, year end) | B6: users | C6: 40000 | D6: 200000 | E6: 600000 | F6: 1500000 | G6: 3000000 | H6: Plan. Today: <500 users. Benchmark: Unstop crossed 20M users (Feb 2025).
A7: Active users (% of registered) | B7: % | C7: 0.35 | D7: 0.35 | E7: 0.35 | F7: 0.35 | G7: 0.35 | H7: Assumption: yearly-active share of registered base
A8: Paid conversion (% of active) | B8: % | C8: 0.02 | D8: 0.03 | E8: 0.035 | F8: 0.04 | G8: 0.045 | H8: Assumption: freemium consumer apps typically 2–5%
A9: Blended revenue per paying user / year | B9: ₹ | C9: 900 | D9: 950 | E9: 1000 | F9: 1050 | G9: 1100 | H9: Mix of Pro ₹149/month and ₹999/year plans (see Pricing)
A10: Pay-per-use revenue per active user / year | B10: ₹ | C10: 5 | D10: 8 | E10: 10 | F10: 12 | G10: 14 | H10: Template unlocks ₹25, Hiero Eval certificate ₹99, interview packs
A11: Colleges (HieroBridge, B2B)
A12: Partner colleges (paying) | B12: # | C12: 5 | D12: 30 | E12: 100 | F12: 250 | G12: 500 | H12: India has 48,246 colleges (AISHE 2023-24)
A13: Average annual contract per college | B13: ₹ | C13: 150000 | D13: 175000 | E13: 200000 | F13: 225000 | G13: 250000 | H13: ≈ ₹300 per student × 500–830 final-year students
A14: Recruiters (HieroConnect, B2B)
A15: Paying recruiters / companies | B15: # | C15: 10 | D15: 60 | E15: 200 | F15: 500 | G15: 1000 | H15: Startups + mid-size firms hiring freshers
A16: Average annual revenue per recruiter | B16: ₹ | C16: 50000 | D16: 60000 | E16: 75000 | F16: 90000 | G16: 100000 | H16: Job-post packs + per-hire fees (see Pricing)
A17: Costs
A18: Headcount (year end) | B18: # | C18: 8 | D18: 14 | E18: 30 | F18: 55 | G18: 90 | H18: Y1 = current core team of 8
A19: Average cost per head / year | B19: ₹ | C19: 360000 | D19: 600000 | E19: 800000 | F19: 900000 | G19: 1000000 | H19: Y1 stipend-level; market salaries from Y2
A20: AI + cloud cost per active user / year | B20: ₹ | C20: 25 | D20: 22 | E20: 20 | F20: 18 | G20: 16 | H20: Groq inference + hosting + MongoDB; falls with scale
A21: Marketing & growth spend | B21: ₹ lakh | C21: 12 | D21: 45 | E21: 120 | F21: 260 | G21: 450 | H21: Campus ambassadors, content, events, performance ads
A22: B2B sales cost (% of college + recruiter revenue) | B22: % | C22: 0.1 | D22: 0.1 | E22: 0.1 | F22: 0.1 | G22: 0.1 | H22: Commissions, travel, demos
A23: Payment gateway fees (% of B2C revenue) | B23: % | C23: 0.02 | D23: 0.02 | E23: 0.02 | F23: 0.02 | G23: 0.02 | H23: Razorpay standard ≈ 2%
A24: G&A (legal, compliance, tools, office) | B24: ₹ lakh | C24: 4 | D24: 12 | E24: 30 | F24: 60 | G24: 100
A25: Tax rate on positive profit (simplified) | B25: % | C25: 0.25 | D25: 0.25 | E25: 0.25 | F25: 0.25 | G25: 0.25 | H25: Simplified: ignores loss carry-forward
A26: Funding & valuation
A27: Seed raise (the ask) | B27: ₹ lakh | C27: 120 | H27: ₹1.2 crore
A28: Equity offered | B28: % | C28: 0.15 | H28: Seed rounds in India typically dilute 15–20%
A29: Future dilution before exit (Series A/B) | B29: % | C29: 0.4 | H29: Assumption
A30: Exit EV / Revenue multiple | B30: x | C30: 4 | H30: Conservative for HR-tech / edtech SaaS
A31: Rupees per lakh | B31: ₹ | C31: 100000 | H31: Unit conversion
A32: Rupees per crore | B32: ₹ | C32: 10000000 | H32: Unit conversion

Sheet Valuation and Ask
A1: The Ask, Valuation & Investor Returns
A2: Targets, not promises — returns depend on execution and later rounds
A4: Item | B4: Unit | C4: Value | D4: How it's calculated
A5: Seed raise (the ask) | B5: ₹ lakh | C5: =Assumptions!C27 -> 120 | D5: Input
A6: Equity offered | B6: % | C6: =Assumptions!C28 -> 0.15 | D6: Input
A7: Post-money valuation | B7: ₹ crore | C7: =IF(C6=0,0,C5/C6)*Assumptions!$C$31/Assumptions!$C$32 -> 8 | D7: Raise ÷ equity
A8: Pre-money valuation | B8: ₹ crore | C8: =C7-C5*Assumptions!$C$31/Assumptions!$C$32 -> 6.8 | D8: Post-money − raise
A10: Year-5 revenue | B10: ₹ crore | C10: =Revenue!G15 -> 29.1675 | D10: From Revenue sheet
A11: Exit EV / Revenue multiple | B11: x | C11: =Assumptions!C30 -> 4 | D11: Input
A12: Implied company value in Year 5 | B12: ₹ crore | C12: =C10*C11 -> 116.67 | D12: Revenue × multiple
A13: Investor stake after future dilution | B13: % | C13: =C6*(1-Assumptions!C29) -> 0.09 | D13: Equity × (1 − later dilution)
A14: Value of investor stake in Year 5 | B14: ₹ crore | C14: =C12*C13 -> 10.5003
A15: Target multiple on investment (MOIC) | B15: x | C15: =IF(C5=0,0,C14/(C5*Assumptions!$C$31/Assumptions!$C$32)) -> 8.75025 | D15: Stake value ÷ investment
A16: Target IRR over 5 years | B16: % | C16: =IF(C15<=0,0,C15^(1/5)-1) -> 0.54313561 | D16: MOIC^(1/5) − 1
A18: Use of funds | B18: Share | C18: ₹ lakh | D18: What it buys
A19: Product & engineering | B19: 0.4 | C19: =B19*$C$5 -> 48 | D19: Ship paywall, Hiero Eval, HieroBridge & HieroConnect v1; 3 engineers for 24 months
A20: Growth & marketing | B20: 0.25 | C20: =B20*$C$5 -> 30 | D20: Campus ambassadors in 50 colleges, content, hackathon/placement events
A21: B2B sales & college partnerships | B21: 0.2 | C21: =B21*$C$5 -> 24 | D21: First 30 college contracts and 60 paying recruiters
A22: AI & cloud infrastructure | B22: 0.08 | C22: =B22*$C$5 -> 9.6 | D22: Inference, hosting and storage for 2 lakh users
A23: Legal, compliance & operations | B23: 0.07 | C23: =B23*$C$5 -> 8.4 | D23: Incorporation, DPIIT, data-protection (DPDP Act) compliance, accounting
A24: Total | B24: =SUM(B19:B23) -> 1 | C24: =SUM(C19:C23) -> 120

Sheet Revenue
A1: Revenue Build (₹ lakh unless stated)
A2: Every figure is a formula driven by the Assumptions sheet
A4: Line | B4: Unit | C4: Y1 (2027) | D4: Y2 (2028) | E4: Y3 (2029) | F4: Y4 (2030) | G4: Y5 (2031) | H4: How it's calculated
A5: User base
A6: Registered users | B6: users | C6: =Assumptions!C6 -> 40000 | D6: =Assumptions!D6 -> 200000 | E6: =Assumptions!E6 -> 600000 | F6: =Assumptions!F6 -> 1500000 | G6: =Assumptions!G6 -> 3000000 | H6: Assumption
A7: Active users | B7: users | C7: =Assumptions!C6*Assumptions!C7 -> 14000 | D7: =Assumptions!D6*Assumptions!D7 -> 70000 | E7: =Assumptions!E6*Assumptions!E7 -> 210000 | F7: =Assumptions!F6*Assumptions!F7 -> 525000 | G7: =Assumptions!G6*Assumptions!G7 -> 1050000 | H7: Registered × active %
A8: Paying subscribers | B8: users | C8: =Assumptions!C6*Assumptions!C7*Assumptions!C8 -> 280 | D8: =Assumptions!D6*Assumptions!D7*Assumptions!D8 -> 2100 | E8: =Assumptions!E6*Assumptions!E7*Assumptions!E8 -> 7350 | F8: =Assumptions!F6*Assumptions!F7*Assumptions!F8 -> 21000 | G8: =Assumptions!G6*Assumptions!G7*Assumptions!G8 -> 47250 | H8: Active × paid conversion
A9: Revenue streams
A10: 1. Hiero Pro subscriptions (B2C) | B10: ₹ lakh | C10: =C8*Assumptions!C9/Assumptions!$C$31 -> 2.52 | D10: =D8*Assumptions!D9/Assumptions!$C$31 -> 19.95 | E10: =E8*Assumptions!E9/Assumptions!$C$31 -> 73.5 | F10: =F8*Assumptions!F9/Assumptions!$C$31 -> 220.5 | G10: =G8*Assumptions!G9/Assumptions!$C$31 -> 519.75 | H10: Paying × revenue per payer
A11: 2. Pay-per-use (templates, Eval certificates, interview packs) | B11: ₹ lakh | C11: =C7*Assumptions!C10/Assumptions!$C$31 -> 0.7 | D11: =D7*Assumptions!D10/Assumptions!$C$31 -> 5.6 | E11: =E7*Assumptions!E10/Assumptions!$C$31 -> 21 | F11: =F7*Assumptions!F10/Assumptions!$C$31 -> 63 | G11: =G7*Assumptions!G10/Assumptions!$C$31 -> 147 | H11: Active × pay-per-use per active
A12: 3. HieroBridge college licences (B2B) | B12: ₹ lakh | C12: =Assumptions!C12*Assumptions!C13/Assumptions!$C$31 -> 7.5 | D12: =Assumptions!D12*Assumptions!D13/Assumptions!$C$31 -> 52.5 | E12: =Assumptions!E12*Assumptions!E13/Assumptions!$C$31 -> 200 | F12: =Assumptions!F12*Assumptions!F13/Assumptions!$C$31 -> 562.5 | G12: =Assumptions!G12*Assumptions!G13/Assumptions!$C$31 -> 1250 | H12: Colleges × contract
A13: 4. HieroConnect recruiter fees (B2B) | B13: ₹ lakh | C13: =Assumptions!C15*Assumptions!C16/Assumptions!$C$31 -> 5 | D13: =Assumptions!D15*Assumptions!D16/Assumptions!$C$31 -> 36 | E13: =Assumptions!E15*Assumptions!E16/Assumptions!$C$31 -> 150 | F13: =Assumptions!F15*Assumptions!F16/Assumptions!$C$31 -> 450 | G13: =Assumptions!G15*Assumptions!G16/Assumptions!$C$31 -> 1000 | H13: Recruiters × revenue per recruiter
A14: Total revenue | B14: ₹ lakh | C14: =SUM(C10:C13) -> 15.72 | D14: =SUM(D10:D13) -> 114.05 | E14: =SUM(E10:E13) -> 444.5 | F14: =SUM(F10:F13) -> 1296 | G14: =SUM(G10:G13) -> 2916.75
A15: Total revenue | B15: ₹ crore | C15: =C14*Assumptions!$C$31/Assumptions!$C$32 -> 0.1572 | D15: =D14*Assumptions!$C$31/Assumptions!$C$32 -> 1.1405 | E15: =E14*Assumptions!$C$31/Assumptions!$C$32 -> 4.445 | F15: =F14*Assumptions!$C$31/Assumptions!$C$32 -> 12.96 | G15: =G14*Assumptions!$C$31/Assumptions!$C$32 -> 29.1675
A16: YoY growth | B16: % | D16: =IF(C14=0,0,D14/C14-1) -> 6.2550891 | E16: =IF(D14=0,0,E14/D14-1) -> 2.8974134 | F16: =IF(E14=0,0,F14/E14-1) -> 1.9156355 | G16: =IF(F14=0,0,G14/F14-1) -> 1.2505787
A17: Revenue mix
A18: B2C share (1+2) | B18: % | C18: =IF(C14=0,0,(C10+C11)/C14) -> 0.20483461 | D18: =IF(D14=0,0,(D10+D11)/D14) -> 0.22402455 | E18: =IF(E14=0,0,(E10+E11)/E14) -> 0.21259843 | F18: =IF(F14=0,0,(F10+F11)/F14) -> 0.21875 | G18: =IF(G14=0,0,(G10+G11)/G14) -> 0.22859347
A19: B2B share (3+4) | B19: % | C19: =IF(C14=0,0,(C12+C13)/C14) -> 0.79516539 | D19: =IF(D14=0,0,(D12+D13)/D14) -> 0.77597545 | E19: =IF(E14=0,0,(E12+E13)/E14) -> 0.78740157 | F19: =IF(F14=0,0,(F12+F13)/F14) -> 0.78125 | G19: =IF(G14=0,0,(G12+G13)/G14) -> 0.77140653

Sheet P&L and Cash
A1: Profit & Loss and Cash (₹ lakh)
A2: Seed of ₹1.2 crore lands at the start of Y1
A4: Line | B4: Unit | C4: Y1 (2027) | D4: Y2 (2028) | E4: Y3 (2029) | F4: Y4 (2030) | G4: Y5 (2031) | H4: How it's calculated
A5: Revenue | B5: ₹ lakh | C5: =Revenue!C14 -> 15.72 | D5: =Revenue!D14 -> 114.05 | E5: =Revenue!E14 -> 444.5 | F5: =Revenue!F14 -> 1296 | G5: =Revenue!G14 -> 2916.75 | H5: From Revenue sheet
A6: Operating costs
A7: Team salaries | B7: ₹ lakh | C7: =Assumptions!C18*Assumptions!C19/Assumptions!$C$31 -> 28.8 | D7: =Assumptions!D18*Assumptions!D19/Assumptions!$C$31 -> 84 | E7: =Assumptions!E18*Assumptions!E19/Assumptions!$C$31 -> 240 | F7: =Assumptions!F18*Assumptions!F19/Assumptions!$C$31 -> 495 | G7: =Assumptions!G18*Assumptions!G19/Assumptions!$C$31 -> 900 | H7: Headcount × cost per head
A8: AI + cloud infrastructure | B8: ₹ lakh | C8: =Revenue!C7*Assumptions!C20/Assumptions!$C$31 -> 3.5 | D8: =Revenue!D7*Assumptions!D20/Assumptions!$C$31 -> 15.4 | E8: =Revenue!E7*Assumptions!E20/Assumptions!$C$31 -> 42 | F8: =Revenue!F7*Assumptions!F20/Assumptions!$C$31 -> 94.5 | G8: =Revenue!G7*Assumptions!G20/Assumptions!$C$31 -> 168 | H8: Active users × cost per active
A9: Marketing & growth | B9: ₹ lakh | C9: =Assumptions!C21 -> 12 | D9: =Assumptions!D21 -> 45 | E9: =Assumptions!E21 -> 120 | F9: =Assumptions!F21 -> 260 | G9: =Assumptions!G21 -> 450 | H9: Assumption
A10: B2B sales cost | B10: ₹ lakh | C10: =(Revenue!C12+Revenue!C13)*Assumptions!C22 -> 1.25 | D10: =(Revenue!D12+Revenue!D13)*Assumptions!D22 -> 8.85 | E10: =(Revenue!E12+Revenue!E13)*Assumptions!E22 -> 35 | F10: =(Revenue!F12+Revenue!F13)*Assumptions!F22 -> 101.25 | G10: =(Revenue!G12+Revenue!G13)*Assumptions!G22 -> 225 | H10: % of B2B revenue
A11: Payment gateway fees | B11: ₹ lakh | C11: =(Revenue!C10+Revenue!C11)*Assumptions!C23 -> 0.0644 | D11: =(Revenue!D10+Revenue!D11)*Assumptions!D23 -> 0.511 | E11: =(Revenue!E10+Revenue!E11)*Assumptions!E23 -> 1.89 | F11: =(Revenue!F10+Revenue!F11)*Assumptions!F23 -> 5.67 | G11: =(Revenue!G10+Revenue!G11)*Assumptions!G23 -> 13.335 | H11: % of B2C revenue
A12: G&A | B12: ₹ lakh | C12: =Assumptions!C24 -> 4 | D12: =Assumptions!D24 -> 12 | E12: =Assumptions!E24 -> 30 | F12: =Assumptions!F24 -> 60 | G12: =Assumptions!G24 -> 100 | H12: Assumption
A13: Total operating costs | B13: ₹ lakh | C13: =SUM(C7:C12) -> 49.6144 | D13: =SUM(D7:D12) -> 165.761 | E13: =SUM(E7:E12) -> 468.89 | F13: =SUM(F7:F12) -> 1016.42 | G13: =SUM(G7:G12) -> 1856.335
A15: EBITDA | B15: ₹ lakh | C15: =C5-C13 -> -33.8944 | D15: =D5-D13 -> -51.711 | E15: =E5-E13 -> -24.39 | F15: =F5-F13 -> 279.58 | G15: =G5-G13 -> 1060.415 | H15: Revenue − costs
A16: EBITDA margin | B16: % | C16: =IF(C5=0,0,C15/C5) -> -2.1561323 | D16: =IF(D5=0,0,D15/D5) -> -0.4534064 | E16: =IF(E5=0,0,E15/E5) -> -0.054870641 | F16: =IF(F5=0,0,F15/F5) -> 0.21572531 | G16: =IF(G5=0,0,G15/G5) -> 0.36356047
A17: Tax | B17: ₹ lakh | C17: =MAX(0,C15)*Assumptions!C25 -> 0 | D17: =MAX(0,D15)*Assumptions!D25 -> 0 | E17: =MAX(0,E15)*Assumptions!E25 -> 0 | F17: =MAX(0,F15)*Assumptions!F25 -> 69.895 | G17: =MAX(0,G15)*Assumptions!G25 -> 265.10375 | H17: Simplified
A18: Net profit / (loss) | B18: ₹ lakh | C18: =C15-C17 -> -33.8944 | D18: =D15-D17 -> -51.711 | E18: =E15-E17 -> -24.39 | F18: =F15-F17 -> 209.685 | G18: =G15-G17 -> 795.31125
A19: Cash
A20: Opening cash | B20: ₹ lakh | C20: =0 -> 0 | D20: =C23 -> 86.1056 | E20: =D23 -> 34.3946 | F20: =E23 -> 10.0046 | G20: =F23 -> 219.6896
A21: Seed funding received | B21: ₹ lakh | C21: =Assumptions!$C$27 -> 120 | D21: =0 -> 0 | E21: =0 -> 0 | F21: =0 -> 0 | G21: =0 -> 0 | H21: The ask, received in Y1
A22: Net profit / (loss) | B22: ₹ lakh | C22: =C18 -> -33.8944 | D22: =D18 -> -51.711 | E22: =E18 -> -24.39 | F22: =F18 -> 209.685 | G22: =G18 -> 795.31125
A23: Closing cash | B23: ₹ lakh | C23: =C20+C21+C22 -> 86.1056 | D23: =D20+D21+D22 -> 34.3946 | E23: =E20+E21+E22 -> 10.0046 | F23: =F20+F21+F22 -> 219.6896 | G23: =G20+G21+G22 -> 1015.0009
A24: Cumulative burn funded by seed | B24: ₹ lakh | C24: =-MIN(0,SUM($C$18:C18)) -> 33.8944 | D24: =-MIN(0,SUM($C$18:D18)) -> 85.6054 | E24: =-MIN(0,SUM($C$18:E18)) -> 109.9954 | F24: =-MIN(0,SUM($C$18:F18)) -> 0 | G24: =-MIN(0,SUM($C$18:G18)) -> 0 | H24: Losses to date
A26: Check: lowest closing cash across 5 years (must stay positive) | C26: =MIN(C23:G23) -> 10.0046 | D26: =IF(C26>0,"OK – seed covers the plan","Needs bridge funding") -> OK – seed covers the plan

Sheet Market TAM SAM SOM
A1: Market Sizing — TAM, SAM, SOM
A2: India-only, bottom-up. Blue = input with source
A4: Input | B4: Unit | C4: Value | D4: Source
A5: Students enrolled in higher education | B5: students | C5: 45000000 | D5: AISHE 2023-24 (Ministry of Education): ~4.5 crore
A6: Students passing out every year | B6: students | C6: 11000000 | D6: AISHE 2022-23 & 2023-24: ~1.09–1.1 crore out-turn per year
A7: Colleges in India | B7: colleges | C7: 48246 | D7: AISHE 2023-24
A8: Colleges we can realistically serve (placement cell, professional courses) | B8: colleges | C8: 10000 | D8: Assumption: ~1 in 5 colleges
A9: Annual career-prep spend per student | B9: ₹ | C9: 1500 | D9: Assumption: resume + interview + one certification per year
A10: Annual contract per college | B10: ₹ | C10: 150000 | D10: Assumption (matches Y1 pricing)
A12: Layer | B12: Unit | C12: Value | D12: Definition
A13: TAM — Total Addressable Market | B13: ₹ crore | C13: =(C5*C9+C7*C10)/Assumptions!$C$32 -> 7473.69 | D13: All higher-ed students × spend + every college × contract
A14: SAM — Serviceable Available Market | B14: ₹ crore | C14: =(C6*C9+C8*C10)/Assumptions!$C$32 -> 1800 | D14: Students graduating each year (job-hunting) + colleges with placement cells
A15: SOM — Serviceable Obtainable Market (Y5 revenue) | B15: ₹ crore | C15: =Revenue!G14*Assumptions!$C$31/Assumptions!$C$32 -> 29.1675 | D15: What Hiero plans to capture by Year 5
A16: SOM as % of SAM | B16: % | C16: =IF(C14=0,0,C15/C14) -> 0.016204167 | D16: Share of SAM needed to hit the plan
A18: Context: India's online higher-education & upskilling market was ₹30,000 crore in FY23, projected ₹85,000 crore by FY28 (23.1% CAGR) — Technopak via BusinessWorld.

Sheet Pricing
A1: Pricing Modules
A2: India-first pricing. Current live promo on hiero.in: template packs at ₹9 / ₹25
A4: Module | B4: Who pays | C4: Price (₹) | D4: Billing | E4: What's included
A5: Hiero Free | B5: Student | C5: 0 | D5: — | E5: 3 resume analyses/month, 1 mock interview, 5 templates, skill-gap report
A6: Hiero Pro — monthly | B6: Student | C6: 149 | D6: per month | E6: Unlimited analyses & JD match, unlimited mock interviews, all 25+ templates, learning paths
A7: Hiero Pro — annual | B7: Student | C7: 999 | D7: per year | E7: Everything in Pro, ~44% cheaper than monthly
A8: Template unlock | B8: Student | C8: 25 | D8: one-time | E8: Premium template pack
A9: Hiero Eval certificate | B9: Student | C9: 99 | D9: per skill | E9: Verified skill test (L1–L3) + named certificate recruiters can trust
A10: Mock interview pack | B10: Student | C10: 49 | D10: 5 interviews | E10: Voice AI interviews with scorecard, for free users
A11: Earn Pro with Hiero Credits | B11: Student | C11: 0 | D11: XP-based | E11: Finish learning/quizzes to unlock Pro free — keeps it fair for students who can't pay
A12: HieroBridge — college licence | B12: College | C12: 300 | D12: per student / year | E12: Placement dashboard, readiness scores, bulk resume + interview access (min ₹1.5 lakh/year)
A13: HieroConnect — job post pack | B13: Recruiter | C13: 4999 | D13: 5 job posts | E13: Post roles, AI-ranked shortlist by verified skills
A14: HieroConnect — hiring plan | B14: Recruiter | C14: 60000 | D14: per year | E14: Unlimited posts, campus drives through HieroBridge, interview links
A15: HieroConnect — per-hire fee | B15: Recruiter | C15: 10000 | D15: per hire | E15: Pay only when a fresher is hired (optional model)

Sheet Competitors
A1: Competitor Analysis
A2: Public information, checked Sep 2026. Ticks = offers the capability end-to-end
A4: Player | B4: What they do | C4: Price to student | D4: Resume score vs JD | E4: AI mock interview | F4: Verified skills | G4: College portal | H4: Recruiter portal | I4: Gap Hiero fills
A5: Hiero | B5: Closed loop: detect gap → learn → prove → match → interview | C5: Free / ₹149 mo | D5: ✔ | E5: ✔ | F5: ✔ | G5: ✔ | H5: ✔ | I5: —
A6: Naukri (Info Edge) | B6: Job board + paid visibility & resume services | C6: Paid tiers from ~₹1,000 | D6: Partial | E6: ✘ | F6: ✘ | G6: ✘ | H6: ✔ | I6: Pays for visibility, doesn't fix the resume or skills
A7: Unstop | B7: Competitions, hackathons, hiring for students (20M users) | C7: Mostly free | D7: ✘ | E7: Partial | F7: Partial | G7: ✔ | H7: ✔ | I7: No personal gap-to-skill loop
A8: Internshala | B8: Internships + paid trainings (₹1,300–1,500 courses) | C8: ₹1,300+ per course | D8: ✘ | E8: ✘ | F8: Partial | G8: ✘ | H8: ✔ | I8: Courses not tied to a specific JD gap
A9: Superset (Great Learning) | B9: Campus placement management software | C9: Free to student (college pays) | D9: ✘ | E9: ✘ | F9: ✘ | G9: ✔ | H9: ✔ | I9: No student preparation layer
A10: Final Round AI | B10: Global AI interview copilot + mock interviews | C10: ~$25/month (~₹2,100) | D10: Partial | E10: ✔ | F10: ✘ | G10: ✘ | H10: ✘ | I10: Too expensive for Indian students; no campus link
A11: ChatGPT / generic AI | B11: DIY resume and interview prompts | C11: Free / ₹1,999 mo | D11: Partial | E11: Partial | F11: ✘ | G11: ✘ | H11: ✘ | I11: Unstructured, no verified proof recruiters trust

Sheet Sources
A1: Sources
A2: Every external number in this workbook and the deck
A4: AISHE 2021-22 summary (43.3M enrolment) | B4: https://educationforallinindia.com/all-india-survey-of-higher-education-aishe-2021-22-summary-of-major-findings/
A5: AISHE 2022-23 & 2023-24 analysis (4.5 cr enrolment, ~1.1 cr out-turn, 48,246 colleges) | B5: https://educationforallinindia.com/analysis-of-aishe-2022-23-and-2023-24-data-by-arun-c-mehta/
A6: India Skills Report 2025 (~55% of graduates employable) | B6: https://vajiramandravi.com/current-affairs/india-skills-report-2025/
A7: Technopak via BusinessWorld: online higher-ed & upskilling ₹30k cr FY23 → ₹85k cr FY28 | B7: https://businessworld.in/article/online-higher-education-and-upskilling-market-to-grow-at-a-cagr-of-231-to-85000-crore-by-fy28-539407
A8: Unstop crosses 20M users (Feb 2025) | B8: https://india.entrepreneur.com/news-and-trends/youth-engagement-and-hiring-platform-unstop-hits-user/486547
A9: Internshala business model & course pricing | B9: https://yourstory.com/2022/07/internshala-blog-profitable-intership-skilling-career-tech-startup/amp
A10: Naukri paid services (~₹1,000+) | B10: https://goodspace.ai/guides/naukri-paid-services-worth-it
A11: Final Round AI pricing (~$25/month) | B11: https://www.stork.ai/en/final-round-ai
A12: Great Learning acquires Superset | B12: https://www.peoplematters.in/news/skilling/byjus-backed-great-learning-acquires-recruitment-platform-superset-32875
A13: Indian seed dilution benchmarks (15–20%, median ticket ~$1M) | B13: https://echai.ventures/startingup/seed-fundraising/how-do-i-actually-value-a-pre-revenue-startup-and-where-does-the-seed-number-come-from
